snmp_lookup/__init__.py
snmp_lookup/__main__.py
snmp_lookup/convert.py
snmp_lookup/helpers.py
snmp_lookup/kind.py
snmp_lookup/maintain.py
snmp_lookup/mibs_enumerator.py
snmp_lookup/point.py
snmp_lookup/selftests.py
snmp_lookup/senml.py
snmp_lookup/validators.py
snmp_lookup/data/__init__.py
snmp_lookup/data/bacs2.csv
snmp_lookup/data/enoc_pdu.csv
snmp_lookup/data/printer.csv
snmp_lookup/data/socomec.csv
snmp_lookup/data/synology.csv
snmp_lookup/data/unifiAP.csv
snmp_lookup/data/unifiSW.csv
snmp_lookup/data/unknown.csv
snmp_lookup/data/ups.csv
snmp_lookup/mibs/BACS2-MIB.py
snmp_lookup/mibs/BRIDGE-MIB.py
snmp_lookup/mibs/BROADCOM-REF-MIB.py
snmp_lookup/mibs/ENOC-MIB.py
snmp_lookup/mibs/FASTPATH-INVENTORY-MIB.py
snmp_lookup/mibs/FASTPATH-LOGGING-MIB.py
snmp_lookup/mibs/FASTPATH-SWITCHING-MIB.py
snmp_lookup/mibs/FROGFOOT-RESOURCES-MIB.py
snmp_lookup/mibs/HCNUM-TC.py
snmp_lookup/mibs/HOST-RESOURCES-MIB.py
snmp_lookup/mibs/IANA-CHARSET-MIB.py
snmp_lookup/mibs/IANA-PRINTER-MIB.py
snmp_lookup/mibs/IANAifType-MIB.py
snmp_lookup/mibs/IF-MIB.py
snmp_lookup/mibs/IP-MIB.py
snmp_lookup/mibs/P-BRIDGE-MIB.py
snmp_lookup/mibs/Printer-MIB.py
snmp_lookup/mibs/Q-BRIDGE-MIB.py
snmp_lookup/mibs/RMON-MIB.py
snmp_lookup/mibs/SNMP-VIEW-BASED-ACM-MIB.py
snmp_lookup/mibs/SNMPv2-MIB.py
snmp_lookup/mibs/SOCOMECUPS-MIB.py
snmp_lookup/mibs/SYNOLOGY-RAID-MIB.py
snmp_lookup/mibs/SYNOLOGY-SMART-MIB.py
snmp_lookup/mibs/SYNOLOGY-STORAGEIO-MIB.py
snmp_lookup/mibs/SYNOLOGY-SYSTEM-MIB.py
snmp_lookup/mibs/TCP-MIB.py
snmp_lookup/mibs/UBNT-MIB.py
snmp_lookup/mibs/UBNT-UniFi-MIB.py
snmp_lookup/mibs/UCD-SNMP-MIB.py
snmp_lookup/mibs/UDP-MIB.py
snmp_lookup/mibs/UPS-MIB.py
snmp_lookup/mibs/__init__.py
snmp_lookup/mibs/index.py
snmp_lookup-1.6.2.dist-info/COPYING.mibs
snmp_lookup-1.6.2.dist-info/LICENSE
snmp_lookup-1.6.2.dist-info/LICENSE.mibs
snmp_lookup-1.6.2.dist-info/METADATA
snmp_lookup-1.6.2.dist-info/WHEEL
snmp_lookup-1.6.2.dist-info/entry_points.txt
snmp_lookup-1.6.2.dist-info/top_level.txt
snmp_lookup-1.6.2.dist-info/RECORD
